<?xml version="1.0" encoding="UTF-8" ?>
<flash_parameters copyright="anvsoftPFMTheme">
    <preferences>
        <global>
            <basic_property movieWidth="650" movieHeight="600" backgroundColor="0x000000" html_title="World Music Listing: Diverse Music Guide" anvsoftMenu="false" enableURL="true" frameRate="30"/>
            <music_property path="" stream="true" loop="true"/>
        </global>
        <thumbnail>
            <basic_property thumWidth="120" thumHeight="100" diameter="500" layerOfThum="13" thumNumOfLayer="5" rotationSpeed="16"/>
        </thumbnail>
    </preferences>
    <album>
        <slide jpegURL="thumbs/t_0001.jpg" d_URL="slides/p_0001.jpg" transition="0" panzoom="1" URLTarget="0" phototime="2" transitiontime="2" url="http://wmlmusicguide.com/single_profile.php?id=425" title="Dolly Parton" width="650" height="600"><![CDATA[Country/Gospel/Pop Artist(e), Musician & Producer]]></slide>
        <slide jpegURL="thumbs/t_0002.jpg" d_URL="slides/p_0002.jpg" transition="0" panzoom="1" URLTarget="0" phototime="2" transitiontime="2" url="http://wmlmusicguide.com/single_profile.php?id=404" title="CK" width="650" height="600"><![CDATA[Dancehall/R&B/Reggae Artist(e)/Model]]></slide>
        <slide jpegURL="thumbs/t_0003.jpg" d_URL="slides/p_0003.jpg" transition="0" panzoom="1" URLTarget="0" phototime="2" transitiontime="2" url="http://wmlmusicguide.com/single_profile.php?id=378" title="Blak Diamon" width="650" height="600"><![CDATA[Dancehall/Pop/Rap/Hip-Hop/Reggae/Soca Artist(e)]]></slide>
        <slide jpegURL="thumbs/t_0004.jpg" d_URL="slides/p_0004.jpg" transition="0" panzoom="1" URLTarget="0" phototime="2" transitiontime="2" url="http://wmlmusicguide.com/single_profile.php?id=418" title="The Band Perry" width="650" height="600"><![CDATA[Country Group/Musicians]]></slide>
        <slide jpegURL="thumbs/t_0005.jpg" d_URL="slides/p_0005.jpg" transition="0" panzoom="1" URLTarget="0" phototime="2" transitiontime="2" url="http://wmlmusicguide.com/single_profile.php?id=427" title="Garth Brooks" width="650" height="600"><![CDATA[Country Artist(e)/Musician]]></slide>
        <slide jpegURL="thumbs/t_0006.jpg" d_URL="slides/p_0006.jpg" transition="0" panzoom="1" URLTarget="0" phototime="2" transitiontime="2" url="http://wmlmusicguide.com/single_profile.php?id=391" title="Jahazeil Myrie" width="650" height="600"><![CDATA[Dancehall/Reggae Artist(e)]]></slide>
        <slide jpegURL="thumbs/t_0007.jpg" d_URL="slides/p_0007.jpg" transition="0" panzoom="1" URLTarget="0" phototime="2" transitiontime="2" url="http://wmlmusicguide.com/single_profile.php?id=373" title="Popcaan" width="650" height="600"><![CDATA[Dancehall/Reggae Artist(e)]]></slide>
        <slide jpegURL="thumbs/t_0008.jpg" d_URL="slides/p_0008.jpg" transition="0" panzoom="1" URLTarget="0" phototime="2" transitiontime="2" url="http://wmlmusicguide.com/single_profile.php?id=406" title="Mink Jo" width="650" height="600"><![CDATA[Pop/Dancehall/Reggae Artist(e)]]></slide>
        <slide jpegURL="thumbs/t_0009.jpg" d_URL="slides/p_0009.jpg" transition="0" panzoom="1" URLTarget="0" phototime="2" transitiontime="2" url="http://wmlmusicguide.com/single_profile.php?id=375" title="LuecMar" width="650" height="600"><![CDATA[Dancehall/R&B/Reggae Artist(e)]]></slide>
        <slide jpegURL="thumbs/t_0010.jpg" d_URL="slides/p_0010.jpg" transition="0" panzoom="1" URLTarget="0" phototime="2" transitiontime="2" url="http://wmlmusicguide.com/single_profile.php?id=376" title="Keely B." width="650" height="600"><![CDATA[Dancehall/Pop/R&B/Reggae Artist(e)]]></slide>
        <slide jpegURL="thumbs/t_0011.jpg" d_URL="slides/p_0011.jpg" transition="0" panzoom="1" URLTarget="0" phototime="2" transitiontime="2" url="http://wmlmusicguide.com/single_profile.php?id=369" title="Kirk Franklin" width="650" height="600"><![CDATA[Gospel/Rap/Hip-Hop Artist(e)/Musician/Producer/Radio Personnel]]></slide>
        <slide jpegURL="thumbs/t_0012.jpg" d_URL="slides/p_0012.jpg" transition="0" panzoom="1" URLTarget="0" phototime="2" transitiontime="2" url="http://wmlmusicguide.com/single_profile.php?id=356" title="Jason Derulo" width="650" height="600"><![CDATA[Pop/R&B Artist(e)]]></slide>
        <slide jpegURL="thumbs/t_0013.jpg" d_URL="slides/p_0013.jpg" transition="0" panzoom="1" URLTarget="0" phototime="2" transitiontime="2" url="http://wmlmusicguide.com/single_profile.php?id=339" title="Iyaz" width="650" height="600"><![CDATA[Pop/R&B/Rap/Hip-Hop Artist(e)]]></slide>
        <slide jpegURL="thumbs/t_0014.jpg" d_URL="slides/p_0014.jpg" transition="0" panzoom="1" URLTarget="0" phototime="2" transitiontime="2" url="http://wmlmusicguide.com/single_profile.php?id=344" title="Denyque" width="650" height="600"><![CDATA[Dancehall/Pop/R&B/Reggae Artist(e)]]></slide>
        <slide jpegURL="thumbs/t_0015.jpg" d_URL="slides/p_0015.jpg" transition="0" panzoom="1" URLTarget="0" phototime="2" transitiontime="2" url="http://wmlmusicguide.com/single_profile.php?id=370" title="Regina Spektor" width="650" height="600"><![CDATA[Gospel/Pop Artist(e)/Musician/Producer]]></slide>
        <slide jpegURL="thumbs/t_0016.jpg" d_URL="slides/p_0016.jpg" transition="0" panzoom="1" URLTarget="0" phototime="2" transitiontime="2" url="http://wmlmusicguide.com/single_profile.php?id=345" title="LMFAO" width="650" height="600"><![CDATA[Dubstep/Pop/Rap/Hip-Hop Group]]></slide>
        <slide jpegURL="thumbs/t_0017.jpg" d_URL="slides/p_0017.jpg" transition="0" panzoom="1" URLTarget="0" phototime="2" transitiontime="2" url="http://wmlmusicguide.com/single_profile.php?id=305" title="Trey Songz" width="650" height="600"><![CDATA[R&B/Rap/Hip-Hop Artist(e)/Producer]]></slide>
        <slide jpegURL="thumbs/t_0018.jpg" d_URL="slides/p_0018.jpg" transition="0" panzoom="1" URLTarget="0" phototime="2" transitiontime="2" url="http://wmlmusicguide.com/single_profile.php?id=321" title="Keith Sweat" width="650" height="600"><![CDATA[R&B Artist(e)/Musician/Producer/Radio Personnel]]></slide>
        <slide jpegURL="thumbs/t_0019.jpg" d_URL="slides/p_0019.jpg" transition="0" panzoom="1" URLTarget="0" phototime="2" transitiontime="2" url="http://wmlmusicguide.com/single_profile.php?id=308" title="Ja&apos;Shayla" width="650" height="600"><![CDATA[Gospel/Pop/R&B Artist(e)]]></slide>
        <slide jpegURL="thumbs/t_0020.jpg" d_URL="slides/p_0020.jpg" transition="0" panzoom="1" URLTarget="0" phototime="2" transitiontime="2" url="http://wmlmusicguide.com/single_profile.php?id=330" title="Sean Kingston" width="650" height="600"><![CDATA[Pop/R&B/Rap/Hip-Hop/Reggae Artist(e)]]></slide>
        <slide jpegURL="thumbs/t_0021.jpg" d_URL="slides/p_0021.jpg" transition="0" panzoom="1" URLTarget="0" phototime="2" transitiontime="2" url="http://wmlmusicguide.com/single_profile.php?id=269" title="Lil&apos; Jon" width="650" height="600"><![CDATA[Pop/Rap/Hip-Hop Artist(e)/Disc Jock/Producer]]></slide>
        <slide jpegURL="thumbs/t_0022.jpg" d_URL="slides/p_0022.jpg" transition="0" panzoom="1" URLTarget="0" phototime="2" transitiontime="2" url="http://wmlmusicguide.com/single_profile.php?id=277" title="Shawn Chrystopher" width="650" height="600"><![CDATA[Rap/Hip-Hop Artist(e)]]></slide>
        <slide jpegURL="thumbs/t_0023.jpg" d_URL="slides/p_0023.jpg" transition="0" panzoom="1" URLTarget="0" phototime="2" transitiontime="2" url="http://wmlmusicguide.com/single_profile.php?id=279" title="Scrappy" width="650" height="600"><![CDATA[Rap/Hip-Hop Artist(e)]]></slide>
        <slide jpegURL="thumbs/t_0024.jpg" d_URL="slides/p_0024.jpg" transition="0" panzoom="1" URLTarget="0" phototime="2" transitiontime="2" url="http://wmlmusicguide.com/single_profile.php?id=273" title="Precious Paris" width="650" height="600"><![CDATA[R&B/Rap/Hip-Hop Artist(e)/Model]]></slide>
        <slide jpegURL="thumbs/t_0025.jpg" d_URL="slides/p_0025.jpg" transition="0" panzoom="1" URLTarget="0" phototime="2" transitiontime="2" url="http://wmlmusicguide.com/single_profile.php?id=285" title="Nickelus F" width="650" height="600"><![CDATA[Rap/Hip-Hop Artist(e)]]></slide>
        <slide jpegURL="thumbs/t_0026.jpg" d_URL="slides/p_0026.jpg" transition="0" panzoom="1" URLTarget="0" phototime="2" transitiontime="2" url="http://wmlmusicguide.com/single_profile.php?id=233" title="Bescenta" width="650" height="600"><![CDATA[Reggae Artist(e)]]></slide>
        <slide jpegURL="thumbs/t_0027.jpg" d_URL="slides/p_0027.jpg" transition="0" panzoom="1" URLTarget="0" phototime="2" transitiontime="2" url="http://wmlmusicguide.com/single_profile.php?id=251" title="Khalilah Rose" width="650" height="600"><![CDATA[Reggae Artist(e)]]></slide>
        <slide jpegURL="thumbs/t_0028.jpg" d_URL="slides/p_0028.jpg" transition="0" panzoom="1" URLTarget="0" phototime="2" transitiontime="2" url="http://wmlmusicguide.com/single_profile.php?id=234" title="Iya Champs" width="650" height="600"><![CDATA[Dancehall/Reggae Artist(e)]]></slide>
        <slide jpegURL="thumbs/t_0029.jpg" d_URL="slides/p_0029.jpg" transition="0" panzoom="1" URLTarget="0" phototime="2" transitiontime="2" url="http://wmlmusicguide.com/single_profile.php?id=232" title="Hempress Sativa" width="650" height="600"><![CDATA[Reggae Artist(e)]]></slide>
        <slide jpegURL="thumbs/t_0030.jpg" d_URL="slides/p_0030.jpg" transition="0" panzoom="1" URLTarget="0" phototime="2" transitiontime="2" url="http://wmlmusicguide.com/single_profile.php?id=258" title="Everton Blender" width="650" height="600"><![CDATA[Reggae Artist(e)]]></slide>
        <slide jpegURL="thumbs/t_0031.jpg" d_URL="slides/p_0031.jpg" transition="0" panzoom="1" URLTarget="0" phototime="2" transitiontime="2" url="http://www.wmlmusicguide.com/m" title="World Music Listing: Diverse Music Guide" width="650" height="600"><![CDATA[Your connection to the music & entertainment industry!]]></slide>
        <slide jpegURL="thumbs/t_0032.jpg" d_URL="slides/p_0032.jpg" transition="0" panzoom="1" URLTarget="0" phototime="2" transitiontime="2" url="http://wmlmusicguide.com/single_profile.php?id=259" title="Sister Carol" width="650" height="600"><![CDATA[Reggae Artist(e)]]></slide>
        <slide jpegURL="thumbs/t_0033.jpg" d_URL="slides/p_0033.jpg" transition="0" panzoom="1" URLTarget="0" phototime="2" transitiontime="2" url="http://wmlmusicguide.com/single_profile.php?id=241" title="Saine" width="650" height="600"><![CDATA[Reggae Artist(e)]]></slide>
        <slide jpegURL="thumbs/t_0034.jpg" d_URL="slides/p_0034.jpg" transition="0" panzoom="1" URLTarget="0" phototime="2" transitiontime="2" url="http://wmlmusicguide.com/single_profile.php?id=231" title="Richie Spice" width="650" height="600"><![CDATA[Reggae Artist(e)]]></slide>
        <slide jpegURL="thumbs/t_0035.jpg" d_URL="slides/p_0035.jpg" transition="0" panzoom="1" URLTarget="0" phototime="2" transitiontime="2" url="http://wmlmusicguide.com/single_profile.php?id=248" title="Morgan Heritage" width="650" height="600"><![CDATA[Reggae Group]]></slide>
        <slide jpegURL="thumbs/t_0036.jpg" d_URL="slides/p_0036.jpg" transition="0" panzoom="1" URLTarget="0" phototime="2" transitiontime="2" url="http://wmlmusicguide.com/single_profile.php?id=247" title="Sophia Squire | Sophire" width="650" height="600"><![CDATA[Reggae Artist(e)]]></slide>
        <slide jpegURL="thumbs/t_0037.jpg" d_URL="slides/p_0037.jpg" transition="0" panzoom="1" URLTarget="0" phototime="2" transitiontime="2" url="http://wmlmusicguide.com/single_profile.php?id=185" title="DJ Camilo" width="650" height="600"><![CDATA[Disc Jock/Radio Personnel]]></slide>
        <slide jpegURL="thumbs/t_0038.jpg" d_URL="slides/p_0038.jpg" transition="0" panzoom="1" URLTarget="0" phototime="2" transitiontime="2" url="http://wmlmusicguide.com/single_profile.php?id=203" title="Alison Hinds" width="650" height="600"><![CDATA[Soca Artist(e)]]></slide>
        <slide jpegURL="thumbs/t_0039.jpg" d_URL="slides/p_0039.jpg" transition="0" panzoom="1" URLTarget="0" phototime="2" transitiontime="2" url="http://wmlmusicguide.com/single_profile.php?id=210" title="Rush" width="650" height="600"><![CDATA[Rock Band]]></slide>
        <slide jpegURL="thumbs/t_0040.jpg" d_URL="slides/p_0040.jpg" transition="0" panzoom="1" URLTarget="0" phototime="2" transitiontime="2" url="http://wmlmusicguide.com/single_profile.php?id=215" title="Creed" width="650" height="600"><![CDATA[Rock Band]]></slide>
        <slide jpegURL="thumbs/t_0041.jpg" d_URL="slides/p_0041.jpg" transition="0" panzoom="1" URLTarget="0" phototime="2" transitiontime="2" url="http://wmlmusicguide.com/single_profile.php?id=190" title="DJ Nikki Z" width="650" height="600"><![CDATA[Disc Jock/Radio Personnel]]></slide>
        <slide jpegURL="thumbs/t_0042.jpg" d_URL="slides/p_0042.jpg" transition="0" panzoom="1" URLTarget="0" phototime="2" transitiontime="2" url="http://wmlmusicguide.com/single_profile.php?id=101" title="Dinearo" width="650" height="600"><![CDATA[Engineer/Producer]]></slide>
        <slide jpegURL="thumbs/t_0043.jpg" d_URL="slides/p_0043.jpg" transition="0" panzoom="1" URLTarget="0" phototime="2" transitiontime="2" url="http://wmlmusicguide.com/single_profile.php?id=100" title="Craig Thelwell" width="650" height="600"><![CDATA[Engineer/Producer]]></slide>
        <slide jpegURL="thumbs/t_0044.jpg" d_URL="slides/p_0044.jpg" transition="0" panzoom="1" URLTarget="0" phototime="2" transitiontime="2" url="http://wmlmusicguide.com/single_profile.php?id=102" title="Anju Blaxxx" width="650" height="600"><![CDATA[Engineer/Producer]]></slide>
        <slide jpegURL="thumbs/t_0045.jpg" d_URL="slides/p_0045.jpg" transition="0" panzoom="1" URLTarget="0" phototime="2" transitiontime="2" url="http://wmlmusicguide.com/single_profile.php?id=171" title="DJ Smurf" width="650" height="600"><![CDATA[Disc Jock/Radio Personnel/Producer]]></slide>
        <slide jpegURL="thumbs/t_0046.jpg" d_URL="slides/p_0046.jpg" transition="0" panzoom="1" URLTarget="0" phototime="2" transitiontime="2" url="http://wmlmusicguide.com/single_profile.php?id=111" title="E. Smitty" width="650" height="600"><![CDATA[Engineer/Producer]]></slide>
        <slide jpegURL="thumbs/t_0047.jpg" d_URL="slides/p_0047.jpg" transition="0" panzoom="1" URLTarget="0" phototime="2" transitiontime="2" url="http://wmlmusicguide.com/single_profile.php?id=109" title="Stephen Depass" width="650" height="600"><![CDATA[Musician (Bass Guitarist)]]></slide>
        <slide jpegURL="thumbs/t_0048.jpg" d_URL="slides/p_0048.jpg" transition="0" panzoom="1" URLTarget="0" phototime="2" transitiontime="2" url="http://wmlmusicguide.com/single_profile.php?id=119" title="Markus Myrie" width="650" height="600"><![CDATA[Dancehall/Pop/R&B/Rap-Hip-Hop/Reggae/Soca Artist(e)/Producer/Engineer]]></slide>
        <slide jpegURL="thumbs/t_0049.jpg" d_URL="slides/p_0049.jpg" transition="0" panzoom="1" URLTarget="0" phototime="2" transitiontime="2" url="http://wmlmusicguide.com/single_profile.php?id=152" title="J.R. Rotem" width="650" height="600"><![CDATA[Producer]]></slide>
        <slide jpegURL="thumbs/t_0050.jpg" d_URL="slides/p_0050.jpg" transition="0" panzoom="1" URLTarget="0" phototime="2" transitiontime="2" url="http://wmlmusicguide.com/single_profile.php?id=132" title="Frank Burt" width="650" height="600"><![CDATA[Musician (Bass Guitarist)/Producer]]></slide>
        <slide jpegURL="thumbs/t_0051.jpg" d_URL="slides/p_0051.jpg" transition="0" panzoom="1" URLTarget="0" phototime="2" transitiontime="2" url="http://wmlmusicguide.com/single_profile.php?id=98" title="Hype Magazine" width="650" height="600"><![CDATA[Magazine]]></slide>
        <slide jpegURL="thumbs/t_0052.jpg" d_URL="slides/p_0052.jpg" transition="0" panzoom="1" URLTarget="0" phototime="2" transitiontime="2" url="http://wmlmusicguide.com/single_profile.php?id=57" title="Eve Lora" width="650" height="600"><![CDATA[Actress, Print/Video Model/Event Hostess]]></slide>
        <slide jpegURL="thumbs/t_0053.jpg" d_URL="slides/p_0053.jpg" transition="0" panzoom="1" URLTarget="0" phototime="2" transitiontime="2" url="http://wmlmusicguide.com/single_profile.php?id=60" title="Devaroe" width="650" height="600"><![CDATA[Print/Video/Promotional Model/Event Hostess]]></slide>
        <slide jpegURL="thumbs/t_0054.jpg" d_URL="slides/p_0054.jpg" transition="0" panzoom="1" URLTarget="0" phototime="2" transitiontime="2" url="http://wmlmusicguide.com/single_profile.php?id=81" title="MarieDriven PR" width="650" height="600"><![CDATA[Marketing/Promotion/Publicist]]></slide>
        <slide jpegURL="thumbs/t_0055.jpg" d_URL="slides/p_0055.jpg" transition="0" panzoom="1" URLTarget="0" phototime="2" transitiontime="2" url="http://wmlmusicguide.com/single_profile.php?id=92" title="Fox Fuse" width="650" height="600"><![CDATA[Distribution/Marketing/Promotion]]></slide>
        <slide jpegURL="thumbs/t_0056.jpg" d_URL="slides/p_0056.jpg" transition="0" panzoom="1" URLTarget="0" phototime="2" transitiontime="2" url="http://wmlmusicguide.com/single_profile.php?id=55" title="Jodian Myrie" width="650" height="600"><![CDATA[Print/Video Model]]></slide>
        <slide jpegURL="thumbs/t_0057.jpg" d_URL="slides/p_0057.jpg" transition="0" panzoom="1" URLTarget="0" phototime="2" transitiontime="2" url="http://wmlmusicguide.com/single_profile.php?id=45" title="Tammie Thelwell" width="650" height="600"><![CDATA[Model/Make-Up Artist]]></slide>
        <slide jpegURL="thumbs/t_0058.jpg" d_URL="slides/p_0058.jpg" transition="0" panzoom="1" URLTarget="0" phototime="2" transitiontime="2" url="http://wmlmusicguide.com/single_profile.php?id=69" title="Sasha Del&apos;Valle" width="650" height="600"><![CDATA[Print/Video Model/Event Hostess/Actress]]></slide>
        <slide jpegURL="thumbs/t_0059.jpg" d_URL="slides/p_0059.jpg" transition="0" panzoom="1" URLTarget="0" phototime="2" transitiontime="2" url="http://wmlmusicguide.com/single_profile.php?id=48" title="Keyshia Ka&apos;Oir" width="650" height="600"><![CDATA[Print/Video Model/Event Hostess/Actress/Ka'Oir Ceo/Rap/Hip-Hop Artist(e)]]></slide>
        <slide jpegURL="thumbs/t_0060.jpg" d_URL="slides/p_0060.jpg" transition="0" panzoom="1" URLTarget="0" phototime="2" transitiontime="2" url="http://wmlmusicguide.com/single_profile.php?id=74" title="Kendra Kouture" width="650" height="600"><![CDATA[Freelance Model/Video Boss/ Hostess]]></slide>
        <slide jpegURL="thumbs/t_0061.jpg" d_URL="slides/p_0061.jpg" transition="0" panzoom="1" URLTarget="0" phototime="2" transitiontime="2" url="http://wmlmusicguide.com/single_profile.php?id=26" title="Yasmeen Sincere" width="650" height="600"><![CDATA[Print/Video Model]]></slide>
        <slide jpegURL="thumbs/t_0062.jpg" d_URL="slides/p_0062.jpg" transition="0" panzoom="1" URLTarget="0" phototime="2" transitiontime="2" url="http://wmlmusicguide.com/single_profile.php?id=7" title="Wayne Lexx" width="650" height="600"><![CDATA[Photographer/Video Director]]></slide>
        <slide jpegURL="thumbs/t_0063.jpg" d_URL="slides/p_0063.jpg" transition="0" panzoom="1" URLTarget="0" phototime="2" transitiontime="2" url="http://wmlmusicguide.com/single_profile.php?id=12" title="Luga Podesta" width="650" height="600"><![CDATA[Video Director]]></slide>
        <slide jpegURL="thumbs/t_0064.jpg" d_URL="slides/p_0064.jpg" transition="0" panzoom="1" URLTarget="0" phototime="2" transitiontime="2" url="http://wmlmusicguide.com/single_profile.php?id=14" title="Icey Jace" width="650" height="600"><![CDATA[Photographer/Video Director]]></slide>
        <slide jpegURL="thumbs/t_0065.jpg" d_URL="slides/p_0065.jpg" transition="0" panzoom="1" URLTarget="0" phototime="2" transitiontime="2" url="http://wmlmusicguide.com/single_profile.php?id=3" title="Dale &quot;Rage&quot; Resteghini" width="650" height="600"><![CDATA[Video Director]]></slide>
    </album>
</flash_parameters>
